{
  "$id": "12007697-58",
  "$schema": "https://schema.yext.com/config/km/entity/v1",
  "primaryLocale": "en",
  "content": {
    "c_degree": "Ph.D., Stanford University, 2003",
    "c_department": [
      "Computer Science"
    ],
    "c_office": "320 Computer Science",
    "c_primaryCTA": {
      "label": "Homepage",
      "link": "https://www.cs.princeton.edu/~ogt",
      "linkType": "OTHER"
    },
    "c_researchInterests": [
      "Bioinformatics",
      "Analysis Of Large-Scale Biological Data Sets",
      "Algorithms For Integration Of Data From Multiple Sources",
      "Visualization Of Biological Data",
      "Machine Learning Methods In Bioinformatics"
    ],
    "c_secondaryCTA": {
      "label": "Profile",
      "link": "https://www.cs.princeton.edu/people/profile/ogt",
      "linkType": "OTHER"
    },
    "description": "Bioinformatics; analysis of large-scale biological data sets (genomics, gene expression, proteomics, biological networks); algorithms for integration of data from multiple data sources; visualization of biological data; machine learning methods in bioinformatics. ISCB Overton Prize 2011; GSA Ira Herskowitz Award 2014.",
    "emails": [
      "ogt@cs.princeton.edu"
    ],
    "mainPhone": "+16092581749",
    "name": "Olga Troyanskaya",
    "photoGallery": [
      {
        "image": {
          "height": 300,
          "sourceUrl": "https://www.cs.princeton.edu/sites/all/modules/custom/cs_people/generate_thumbnail.php?id\u003d33\u0026amp;thumb\u003d",
          "thumbnails": [
            {
              "height": 300,
              "url": "http://a.mktgcdn.com/p-sandbox/LYPiM-PfpFCQa4_TZLxcfczWHhNfGXbrfNBoTSvG1oU/200x300.jpg",
              "width": 200
            },
            {
              "height": 294,
              "url": "http://a.mktgcdn.com/p-sandbox/LYPiM-PfpFCQa4_TZLxcfczWHhNfGXbrfNBoTSvG1oU/196x294.jpg",
              "width": 196
            }
          ],
          "url": "http://a.mktgcdn.com/p-sandbox/LYPiM-PfpFCQa4_TZLxcfczWHhNfGXbrfNBoTSvG1oU/200x300.jpg",
          "width": 200
        }
      }
    ],
    "title": "Professor"
  },
  "entityType": "ce_faculty",
  "labels": []
}